ehsaneddintk/__init__.py
ehsaneddintk/fileutil/__init__.py
ehsaneddintk/fileutil/fileutil.py
ehsaneddintk/math/__init__.py
ehsaneddintk/visualization/__init__.py
EhsaneddinToolkit-0.1.0.dist-info/LICENSE
EhsaneddinToolkit-0.1.0.dist-info/METADATA
EhsaneddinToolkit-0.1.0.dist-info/WHEEL
EhsaneddinToolkit-0.1.0.dist-info/top_level.txt
EhsaneddinToolkit-0.1.0.dist-info/RECORD
